<?xml version="1.0" encoding="utf-8" ?>
<XnaContent>
  <Asset Type="MiRo.SimHexWorld.Engine.Types.Civilization">
    <Name>English</Name>
    <Title>TXT_KEY_CIVIZATION_ENGLISH_TITLE</Title>
    <Description>TXT_KEY_CIVIZATION_ENGLISH_DESCRIPTION</Description>
    <ImageName>English</ImageName>
    <UniqueUnits>
      <Item>Longbowman</Item>
      <Item>ShipOfTheLine</Item>
    </UniqueUnits>
    <UniqueBuildings></UniqueBuildings>
    <StartingTechNames>
      <Item>Agriculture</Item>
    </StartingTechNames>
    <Duration>55 BC (Romans) - present </Duration>
    <Location>Western Coast of Europe</Location>
    <Size>94,251 sq miles </Size>
    <Capital>London</Capital>
    <Cities>
      <Item>York</Item>
      <Item>Nottingham</Item>
      <Item>Hastings</Item>
      <Item>Canterbury</Item>
      <Item>Coventry</Item>
      <Item>Warwick</Item>
      <Item>Newcastle</Item>
      <Item>Oxford</Item>
      <Item>Liverpool</Item>
      <Item>Dover</Item>
      <Item>Brighton</Item>
      <Item>Norwich</Item>
      <Item>Leeds</Item>
      <Item>Reading</Item>
      <Item>Birmingham</Item>
      <Item>Richmond</Item>
      <Item>Exeter</Item>
      <Item>Cambridge</Item>
      <Item>Gloucester</Item>
      <Item>Manchester</Item>
      <Item>Bristol</Item>
      <Item>Leicester</Item>
      <Item>Carlisle</Item>
      <Item>Ipswich</Item>
      <Item>Portsmouth</Item>
      <Item>Berwick</Item>
      <Item>Bath</Item>
      <Item>Mumbles</Item>
      <Item>Southampton</Item>
      <Item>Sheffield</Item>
      <Item>Salisbury</Item>
      <Item>Colchester</Item>
      <Item>Plymouth</Item>
      <Item>Lancaster</Item>
      <Item>Blackpool</Item>
      <Item>Winchester</Item>
      <Item>Hull</Item>
    </Cities>
  </Asset>
</XnaContent>
